pysvg2csv/__init__.py
pysvg2csv/core/__init__.py
pysvg2csv/core/svg2csv.py
pysvg2csv/utils/__init__.py
pysvg2csv/utils/utils.py
pysvg2csv-2025.10.2.dist-info/licenses/LICENSE
pysvg2csv-2025.10.2.dist-info/METADATA
pysvg2csv-2025.10.2.dist-info/WHEEL
pysvg2csv-2025.10.2.dist-info/top_level.txt
pysvg2csv-2025.10.2.dist-info/RECORD
