Metadata-Version: 2.4
Name: pysvg2csv
Version: 2025.10.2
Summary: Package to convert SVG paths to CSV data and LaTeX commands
Author-email: Amit Manohar Manthanwar <manthanwar@hotmail.com>
Project-URL: repository, https://github.com/manthanwar/pysvg2csv
Requires-Python: >=3.12
License-File: LICENSE
Provides-Extra: test
Requires-Dist: pytest; extra == "test"
Requires-Dist: pytest-cov; extra == "test"
Dynamic: license-file
